MANIFEST.in
account_chart.xml
account_tax.xml
account_tax_code.xml
l10n_chart_ec_wizard.xml
setup.py
./__init__.py
./__openerp__.py
i18n/ar.po
i18n/ca.po
i18n/da.po
i18n/es.po
i18n/es_CR.po
i18n/es_EC.po
i18n/es_MX.po
i18n/es_PY.po
i18n/es_VE.po
i18n/fr.po
i18n/gl.po
i18n/it.po
i18n/l10n_ec.pot
i18n/nl.po
i18n/pt.po
i18n/pt_BR.po
i18n/sl.po
i18n/tr.po
images/config_chart_l10n_ec.jpeg
images/l10n_ec_chart.jpeg
openerp_l10n_ec.egg-info/PKG-INFO
openerp_l10n_ec.egg-info/SOURCES.txt
openerp_l10n_ec.egg-info/dependency_links.txt
openerp_l10n_ec.egg-info/requires.txt
openerp_l10n_ec.egg-info/top_level.txt
static/src/img/icon.png